gothic/__init__.py
gothic/main.py
gothic/tests.py
gothic/utils.py
gothic-0.0.1.dist-info/LICENSE
gothic-0.0.1.dist-info/METADATA
gothic-0.0.1.dist-info/WHEEL
gothic-0.0.1.dist-info/entry_points.txt
gothic-0.0.1.dist-info/top_level.txt
gothic-0.0.1.dist-info/RECORD
